maimai_py/__init__.py
maimai_py/api.py
maimai_py/enums.py
maimai_py/exceptions.py
maimai_py/maimai.py
maimai_py/models.py
maimai_py/providers/__init__.py
maimai_py/providers/arcade.py
maimai_py/providers/base.py
maimai_py/providers/divingfish.py
maimai_py/providers/hybrid.py
maimai_py/providers/local/__init__.py
maimai_py/providers/local/areas_ja.json
maimai_py/providers/local/areas_zh.json
maimai_py/providers/local/charas.json
maimai_py/providers/local/frames.json
maimai_py/providers/local/icons.json
maimai_py/providers/local/nameplates.json
maimai_py/providers/local/partners.json
maimai_py/providers/local/trophies.json
maimai_py/providers/lxns.py
maimai_py/providers/wechat.py
maimai_py/providers/yuzu.py
maimai_py/utils/__init__.py
maimai_py/utils/coefficient.py
maimai_py/utils/page_parser.py
maimai_py/utils/sentinel.py
maimai_py-1.3.7.dist-info/METADATA
maimai_py-1.3.7.dist-info/WHEEL
maimai_py-1.3.7.dist-info/entry_points.txt
maimai_py-1.3.7.dist-info/licenses/LICENSE
maimai_py-1.3.7.dist-info/RECORD
