Metadata-Version: 2.4
Name: maimai-py
Version: 1.3.7
Summary: The definitive python wrapper for MaimaiCN.
License: MIT
License-File: LICENSE
Author: Usagi no Niku
Author-email: chenbohan911@163.com
Requires-Python: >=3.9,<4.0
Classifier: License :: OSI Approved :: MIT License
Classifier: Programming Language :: Python :: 3
Classifier: Programming Language :: Python :: 3.9
Classifier: Programming Language :: Python :: 3.10
Classifier: Programming Language :: Python :: 3.11
Classifier: Programming Language :: Python :: 3.12
Classifier: Programming Language :: Python :: 3.13
Classifier: Programming Language :: Python :: 3.14
Requires-Dist: aiocache (>=0.12.3,<0.13.0)
Requires-Dist: cryptography (>=38.0)
Requires-Dist: httpcore (>=1.0.9,<2.0.0)
Requires-Dist: httpx (>=0.28.0,<0.29.0)
Requires-Dist: lxml (>=5.4.0,<6.0.0)
Requires-Dist: maimai-ffi (==0.6.0)
Requires-Dist: tenacity (>=9.1.2,<10.0.0)
